Topsis_Devansh_102303631/__init__.py
Topsis_Devansh_102303631/topsis.py
topsis_devansh_102303631-1.0.0.dist-info/METADATA
topsis_devansh_102303631-1.0.0.dist-info/WHEEL
topsis_devansh_102303631-1.0.0.dist-info/entry_points.txt
topsis_devansh_102303631-1.0.0.dist-info/top_level.txt
topsis_devansh_102303631-1.0.0.dist-info/RECORD
